beetsplug/__init__.py
beetsplug/vtalbumartist.py
beets_vtalbumartist-1.1.0.dist-info/LICENSE
beets_vtalbumartist-1.1.0.dist-info/METADATA
beets_vtalbumartist-1.1.0.dist-info/WHEEL
beets_vtalbumartist-1.1.0.dist-info/top_level.txt
beets_vtalbumartist-1.1.0.dist-info/RECORD
