Metadata-Version: 2.1
Name: beets-vtalbumartist
Version: 1.1.0
Summary: Beets plugin that provides a customizable flexible field/tag, vt_albumartist, which defaults to the track's albumartist.
Home-page: https://github.com/rafaelparente/beets-vtalbumartist
Author: Rafael Parente
Author-email: rafaelp.dev@gmail.com
License: MIT
Platform: UNKNOWN
Classifier: Development Status :: 5 - Production/Stable
Classifier: Environment :: Plugins
Classifier: License :: OSI Approved :: MIT License
Classifier: Programming Language :: Python
Classifier: Programming Language :: Python :: 3
Classifier: Programming Language :: Python :: 3.4
Classifier: Programming Language :: Python :: Implementation :: CPython
Classifier: Programming Language :: Python :: Implementation :: PyPy
Classifier: Topic :: Multimedia :: Sound/Audio
Requires-Python: >=3.4.0
Requires-Dist: beets
